{
  "rank": "hr",
  "pieces": [
    {
      "part": "head",
      "skills": [
        {
          "name": "Evade Window",
          "level": 2
        },
        {
          "name": "Botanist",
          "level": 1
        }
      ],
      "name": "King Beetle Vertex Alpha",
      "slots": [
        0,
        0,
        0
      ]
    },
    {
      "part": "chest",
      "skills": [
        {
          "name": "Quick Sheath",
          "level": 2
        },
        {
          "name": "Botanist",
          "level": 1
        }
      ],
      "name": "King Beetle Thorax Alpha",
      "slots": [
        0,
        0,
        0
      ]
    },
    {
      "part": "arm",
      "skills": [
        {
          "name": "Botanist",
          "level": 2
        },
        {
          "name": "Leap of Faith",
          "level": 1
        }
      ],
      "name": "King Beetle Brachia Alpha",
      "slots": [
        1,
        0,
        0
      ]
    },
    {
      "part": "waist",
      "skills": [
        {
          "name": "Honey Hunter",
          "level": 1
        },
        {
          "name": "Quick Sheath",
          "level": 1
        }
      ],
      "name": "King Beetle Elytra Alpha",
      "slots": [
        1,
        0,
        0
      ]
    },
    {
      "part": "leg",
      "skills": [
        {
          "name": "Forager's Luck",
          "level": 1
        },
        {
          "name": "Evade Window",
          "level": 1
        }
      ],
      "name": "King Beetle Crura Alpha",
      "slots": [
        1,
        0,
        0
      ]
    }
  ],
  "set": "King Beetle Alpha Set",
  "rarity": 5
}